data_and_reporting_sdk-2.0.0.dist-info/licenses/LICENSE
shelldatareportingapis/__init__.py
shelldatareportingapis/api_helper.py
shelldatareportingapis/configuration.py
shelldatareportingapis/shelldatareportingapis_client.py
shelldatareportingapis/controllers/__init__.py
shelldatareportingapis/controllers/base_controller.py
shelldatareportingapis/controllers/customer_controller.py
shelldatareportingapis/controllers/invoice_controller.py
shelldatareportingapis/controllers/o_auth_authorization_controller.py
shelldatareportingapis/controllers/transaction_controller.py
shelldatareportingapis/exceptions/__init__.py
shelldatareportingapis/exceptions/api_exception.py
shelldatareportingapis/exceptions/error_object_exception.py
shelldatareportingapis/exceptions/o_auth_provider_exception.py
shelldatareportingapis/http/__init__.py
shelldatareportingapis/http/http_call_back.py
shelldatareportingapis/http/http_method_enum.py
shelldatareportingapis/http/http_request.py
shelldatareportingapis/http/http_response.py
shelldatareportingapis/http/auth/__init__.py
shelldatareportingapis/http/auth/o_auth_2.py
shelldatareportingapis/models/__init__.py
shelldatareportingapis/models/account_access.py
shelldatareportingapis/models/account_req.py
shelldatareportingapis/models/account_request.py
shelldatareportingapis/models/account_res.py
shelldatareportingapis/models/account_response_accounts_items.py
shelldatareportingapis/models/accounts.py
shelldatareportingapis/models/address.py
shelldatareportingapis/models/associated_account.py
shelldatareportingapis/models/audit_array_elements.py
shelldatareportingapis/models/audit_req.py
shelldatareportingapis/models/audit_request.py
shelldatareportingapis/models/audit_response.py
shelldatareportingapis/models/audit_response_audits_items.py
shelldatareportingapis/models/bank_account.py
shelldatareportingapis/models/bonus_configuration.py
shelldatareportingapis/models/bonus_history.py
shelldatareportingapis/models/card_day_time_restrictions.py
shelldatareportingapis/models/card_exceptions.py
data_and_reporting_sdk-2.0.0.dist-info/METADATA
data_and_reporting_sdk-2.0.0.dist-info/WHEEL
data_and_reporting_sdk-2.0.0.dist-info/top_level.txt
data_and_reporting_sdk-2.0.0.dist-info/RECORD
