Metadata-Version: 2.4
Name: data-and-reporting-sdk
Version: 2.0.0
Summary: Data And Reporting product consists of API's which provides details of transaction and invoice informations about shell cards. 
Author-email: developer sdksio <developer+sdksio@apimatic.io>
Project-URL: Documentation, https://developer.shell.com/product-catalog/data-and-reporting-premium/sdk#/http/setting-up-sdks
Keywords: Shell,DataAndReporting,APIMatic,SDKs,APIs
Requires-Python: >=3.7
License-File: LICENSE
Requires-Dist: apimatic-core>=0.2.20,~=0.2.0
Requires-Dist: apimatic-core-interfaces>=0.1.5,~=0.1.0
Requires-Dist: apimatic-requests-client-adapter>=0.1.6,~=0.1.0
Provides-Extra: testutils
Requires-Dist: pytest>=7.2.2; extra == "testutils"
Dynamic: license-file
